chiaroscuro_forge.py
chiaroscuro_forge-0.2.1.dist-info/licenses/LICENSE
chiaroscuro_forge-0.2.1.dist-info/METADATA
chiaroscuro_forge-0.2.1.dist-info/WHEEL
chiaroscuro_forge-0.2.1.dist-info/entry_points.txt
chiaroscuro_forge-0.2.1.dist-info/top_level.txt
chiaroscuro_forge-0.2.1.dist-info/RECORD
