Metadata-Version: 2.4
Name: chiaroscuro-forge
Version: 0.2.1
Summary: An intelligent image enhancement tool inspired by Renaissance techniques
Home-page: https://github.com/MichailSemoglou/chiaroscuro-forge
Author: Michail Semoglou
Author-email: m.semoglou@tongji.edu.cn
License: MIT
Project-URL: Source, https://github.com/MichailSemoglou/chiaroscuro-forge
Project-URL: Issues, https://github.com/MichailSemoglou/chiaroscuro-forge/issues
Classifier: Programming Language :: Python :: 3
Classifier: Programming Language :: Python :: 3 :: Only
Classifier: License :: OSI Approved :: MIT License
Classifier: Operating System :: OS Independent
Classifier: Topic :: Multimedia :: Graphics
Classifier: Topic :: Scientific/Engineering :: Image Processing
Requires-Python: >=3.7
License-File: LICENSE
Requires-Dist: numpy>=1.20.0
Requires-Dist: scipy>=1.7.0
Requires-Dist: scikit-image>=0.18.0
Dynamic: author
Dynamic: author-email
Dynamic: classifier
Dynamic: description
Dynamic: description-content-type
Dynamic: home-page
Dynamic: license
Dynamic: license-file
Dynamic: project-url
Dynamic: requires-dist
Dynamic: requires-python
Dynamic: summary
